py_moysklad/__init__.py
py_moysklad/client.py
py_moysklad/clients/__init__.py
py_moysklad/clients/entity_client.py
py_moysklad/clients/generic.py
py_moysklad/clients/product_client.py
py_moysklad/entities/__init__.py
py_moysklad/entities/address.py
py_moysklad/entities/agents/__init__.py
py_moysklad/entities/agents/agent.py
py_moysklad/entities/agents/counterparty.py
py_moysklad/entities/agents/employee.py
py_moysklad/entities/agents/organization.py
py_moysklad/entities/assortment.py
py_moysklad/entities/attached_file.py
py_moysklad/entities/attachment.py
py_moysklad/entities/attribute.py
py_moysklad/entities/barcode.py
py_moysklad/entities/cashier.py
py_moysklad/entities/context.py
py_moysklad/entities/country.py
py_moysklad/entities/currency.py
py_moysklad/entities/discounts/__init__.py
py_moysklad/entities/discounts/accumulation_discount.py
py_moysklad/entities/discounts/bonus_program.py
py_moysklad/entities/discounts/discount.py
py_moysklad/entities/discounts/good_discount.py
py_moysklad/entities/discounts/personal_discount.py
py_moysklad/entities/discounts/round_off_discount.py
py_moysklad/entities/discounts/special_price_discount.py
py_moysklad/entities/documents/__init__.py
py_moysklad/entities/documents/positions/__init__.py
py_moysklad/entities/entity.py
py_moysklad/entities/group.py
py_moysklad/entities/image.py
py_moysklad/entities/meta.py
py_moysklad/entities/meta_entity.py
py_moysklad/entities/price.py
py_moysklad/entities/price_type.py
py_moysklad/entities/product_folder.py
py_moysklad/entities/products/__init__.py
py_moysklad/entities/products/abstract_product.py
py_moysklad/entities/products/good_payment_item_type.py
py_moysklad/entities/products/good_tax_system.py
py_moysklad/entities/products/product.py
py_moysklad/entities/region.py
py_moysklad/entities/state.py
py_moysklad/entities/store.py
py_moysklad/entities/uom.py
py_moysklad/exceptions.py
py_moysklad/http.py
py_moysklad/responses/__init__.py
py_moysklad/responses/list_entity.py
py_moysklad-0.1.0.dist-info/LICENSE
py_moysklad-0.1.0.dist-info/WHEEL
py_moysklad-0.1.0.dist-info/METADATA
py_moysklad-0.1.0.dist-info/RECORD
