Metadata-Version: 2.1
Name: py-moysklad
Version: 0.1.0
Summary: 
Author: NerV
Author-email: voldemar.krs@gmail.com
Requires-Python: >=3.9,<4.0
Classifier: Programming Language :: Python :: 3
Classifier: Programming Language :: Python :: 3.10
Classifier: Programming Language :: Python :: 3.9
Requires-Dist: api-client (>=1.3.1,<2.0.0)
Requires-Dist: pydantic (>=1.8.2,<2.0.0)
